pretix_mollie/__init__.py
pretix_mollie/apps.py
pretix_mollie/forms.py
pretix_mollie/payment.py
pretix_mollie/signals.py
pretix_mollie/urls.py
pretix_mollie/utils.py
pretix_mollie/views.py
pretix_mollie/locale/django.pot
pretix_mollie/locale/ca/LC_MESSAGES/django.mo
pretix_mollie/locale/ca/LC_MESSAGES/django.po
pretix_mollie/locale/da/LC_MESSAGES/django.mo
pretix_mollie/locale/da/LC_MESSAGES/django.po
pretix_mollie/locale/de/LC_MESSAGES/django.mo
pretix_mollie/locale/de/LC_MESSAGES/django.po
pretix_mollie/locale/de_Informal/.gitkeep
pretix_mollie/locale/de_Informal/LC_MESSAGES/django.mo
pretix_mollie/locale/de_Informal/LC_MESSAGES/django.po
pretix_mollie/locale/el/LC_MESSAGES/django.mo
pretix_mollie/locale/el/LC_MESSAGES/django.po
pretix_mollie/locale/fi/LC_MESSAGES/django.mo
pretix_mollie/locale/fi/LC_MESSAGES/django.po
pretix_mollie/locale/fo/LC_MESSAGES/django.mo
pretix_mollie/locale/fo/LC_MESSAGES/django.po
pretix_mollie/locale/fr/LC_MESSAGES/django.mo
pretix_mollie/locale/fr/LC_MESSAGES/django.po
pretix_mollie/locale/hr/LC_MESSAGES/django.mo
pretix_mollie/locale/hr/LC_MESSAGES/django.po
pretix_mollie/locale/ja/LC_MESSAGES/django.mo
pretix_mollie/locale/ja/LC_MESSAGES/django.po
pretix_mollie/locale/lb/LC_MESSAGES/django.mo
pretix_mollie/locale/lb/LC_MESSAGES/django.po
pretix_mollie/locale/lv/LC_MESSAGES/django.mo
pretix_mollie/locale/lv/LC_MESSAGES/django.po
pretix_mollie/locale/nb_NO/LC_MESSAGES/django.mo
pretix_mollie/locale/nb_NO/LC_MESSAGES/django.po
pretix_mollie/locale/nl/LC_MESSAGES/django.mo
pretix_mollie/locale/nl/LC_MESSAGES/django.po
pretix_mollie/locale/nl_Informal/LC_MESSAGES/django.mo
pretix_mollie/locale/nl_Informal/LC_MESSAGES/django.po
pretix_mollie/locale/pl/LC_MESSAGES/django.mo
pretix_mollie/locale/pl/LC_MESSAGES/django.po
pretix_mollie/locale/pl_Informal/LC_MESSAGES/django.mo
pretix_mollie/locale/pl_Informal/LC_MESSAGES/django.po
pretix_mollie/locale/pt/LC_MESSAGES/django.mo
pretix_mollie/locale/pt/LC_MESSAGES/django.po
pretix_mollie-2.5.1.dist-info/licenses/LICENSE
pretix_mollie-2.5.1.dist-info/METADATA
pretix_mollie-2.5.1.dist-info/WHEEL
pretix_mollie-2.5.1.dist-info/entry_points.txt
pretix_mollie-2.5.1.dist-info/top_level.txt
pretix_mollie-2.5.1.dist-info/RECORD
