Metadata-Version: 2.4
Name: pretix-mollie
Version: 2.5.1
Summary: Integration for the Mollie payment provider.
Author-email: pretix team <support@pretix.eu>
Maintainer-email: pretix team <support@pretix.eu>
License: Copyright 2018 Raphael Michel
Project-URL: homepage, https://github.com/pretix/pretix-mollie
Keywords: pretix
Requires-Python: >=3.9
License-File: LICENSE
Dynamic: license-file
